odoo10_addon_base_export_security-10.0.1.0.0-py2.7-nspkg.pth
odoo/addons/base_export_security/README.rst
odoo/addons/base_export_security/__init__.py
odoo/addons/base_export_security/__manifest__.py
odoo/addons/base_export_security/data/export.xml
odoo/addons/base_export_security/models/__init__.py
odoo/addons/base_export_security/models/base.py
odoo/addons/base_export_security/models/export.py
odoo/addons/base_export_security/security/export_security.xml
odoo/addons/base_export_security/security/ir.model.access.csv
odoo/addons/base_export_security/static/description/export_log.png
odoo/addons/base_export_security/static/description/export_menu_item_hidden.png
odoo/addons/base_export_security/static/description/export_notification.png
odoo/addons/base_export_security/static/src/js/base_export_security.js
odoo/addons/base_export_security/static/tests/js/base_export_security.js
odoo/addons/base_export_security/tests/__init__.py
odoo/addons/base_export_security/tests/test_export.py
odoo/addons/base_export_security/views/export_view.xml
odoo10_addon_base_export_security-10.0.1.0.0.dist-info/DESCRIPTION.rst
odoo10_addon_base_export_security-10.0.1.0.0.dist-info/METADATA
odoo10_addon_base_export_security-10.0.1.0.0.dist-info/RECORD
odoo10_addon_base_export_security-10.0.1.0.0.dist-info/WHEEL
odoo10_addon_base_export_security-10.0.1.0.0.dist-info/metadata.json
odoo10_addon_base_export_security-10.0.1.0.0.dist-info/namespace_packages.txt
odoo10_addon_base_export_security-10.0.1.0.0.dist-info/top_level.txt
